.gitignore
MANIFEST.in
README.rst
bootstrap.py
buildout.cfg
setup.py
collective/__init__.py
collective.contentrules.yearmonth.egg-info/PKG-INFO
collective.contentrules.yearmonth.egg-info/SOURCES.txt
collective.contentrules.yearmonth.egg-info/dependency_links.txt
collective.contentrules.yearmonth.egg-info/entry_points.txt
collective.contentrules.yearmonth.egg-info/namespace_packages.txt
collective.contentrules.yearmonth.egg-info/not-zip-safe
collective.contentrules.yearmonth.egg-info/requires.txt
collective.contentrules.yearmonth.egg-info/top_level.txt
collective/contentrules/__init__.py
collective/contentrules/yearmonth/__init__.py
collective/contentrules/yearmonth/configure.zcml
collective/contentrules/yearmonth/interfaces.py
collective/contentrules/yearmonth/target_folder.py
collective/contentrules/yearmonth/actions/__init__.py
collective/contentrules/yearmonth/actions/configure.zcml
collective/contentrules/yearmonth/actions/move.py
collective/contentrules/yearmonth/tests/__init__.py
collective/contentrules/yearmonth/tests/test_action_move.py
docs/HISTORY.txt
docs/INSTALL.txt
docs/LICENSE.GPL
docs/LICENSE.txt