Metadata-Version: 1.0
Name: collective.contentrules.yearmonth
Version: 1.1
Summary: Moves contents to a choosen directory/YEAR/MONTH
Home-page: http://redomino.com
Author: Davide Moro
Author-email: davide.moro@redomino.com
License: GPL
Keywords: plone
Platform: UNKNOWN
Classifier: Framework :: Plone
Classifier: Programming Language :: Python
Classifier: Framework :: Plone :: 4.0
Classifier: Framework :: Plone :: 4.1
Classifier: Framework :: Plone :: 4.2
